harvester/__init__.py
harvester/extract/__init__.py
harvester/extract/dcatus.py
harvester/load/__init__.py
harvester/load/ckan.py
harvester/utils/__init__.py
harvester/utils/json.py
harvester/validate/__init__.py
harvester/validate/dcat_us.py
datagovharvester-0.1.0.dist-info/LICENSE.md
datagovharvester-0.1.0.dist-info/METADATA
datagovharvester-0.1.0.dist-info/WHEEL
datagovharvester-0.1.0.dist-info/RECORD
