Metadata-Version: 2.1
Name: datagovharvester
Version: 0.1.0
Summary: 
Author: Jin-Sun-tts
Author-email: jin.sun@gsa.gov
Requires-Python: >=3.9
Classifier: Programming Language :: Python :: 3
Classifier: Programming Language :: Python :: 3.9
Classifier: Programming Language :: Python :: 3.10
Classifier: Programming Language :: Python :: 3.11
Classifier: Programming Language :: Python :: 3.12
Requires-Dist: ckanapi (>=4.7,<5.0)
Requires-Dist: deepdiff (>=6.3.0,<7.0.0)
Requires-Dist: jsonschema (>=4.17.3,<5.0.0)
Requires-Dist: pytest (>=7.3.2,<8.0.0)
Requires-Dist: python-dotenv (>=1.0.0,<2.0.0)
Requires-Dist: requests (>=2.31.0,<3.0.0)
